{"personas": [{"nombre": 1, "id": "Farlee", "apellido": "Reicharz", "email": "freicharz0@so-net.ne.jp", "genero": "Male", "edad": 44}, {"nombre": 2, "id": "Urson", "apellido": "de Cullip", "email": "udecullip1@bravesites.com", "genero": "Male", "edad": 22}, {"nombre": 3, "id": "Jere", "apellido": "Tolley", "email": "jtolley2@smugmug.com", "genero": "Male", "edad": 64}, {"nombre": 4, "id": "Charline", "apellido": "Elldred", "email": "celldred3@reddit.com", "genero": "Female", "edad": 53}, {"nombre": 5, "id": "Tedi", "apellido": "Ogus", "email": "togus4@ifeng.com", "genero": "Female", "edad": 47}, {"nombre": 6, "id": "Rollins", "apellido": "Gould", "email": "rgould5@github.com", "genero": "Male", "edad": 34}, {"nombre": 7, "id": "Sylvan", "apellido": "Clementel", "email": "sclementel6@joomla.org", "genero": "Male", "edad": 27}, {"nombre": 8, "id": "Tomi", "apellido": "Lindner", "email": "tlindner7@theguardian.com", "genero": "Female", "edad": 28}, {"nombre": 9, "id": "Karina", "apellido": "Ryrie", "email": "kryrie8@ucoz.com", "genero": "Female", "edad": 65}, {"nombre": 10, "id": "Keefe", "apellido": "Clemenza", "email": "kclemenza9@ow.ly", "genero": "Male", "edad": 59}, {"nombre": 11, "id": "Dario", "apellido": "Leband", "email": "dlebanda@youku.com", "genero": "Male", "edad": 52}, {"nombre": 12, "id": "Margit", "apellido": "Mocker", "email": "mmockerb@cnbc.com", "genero": "Female", "edad": 22}, {"nombre": 13, "id": "Roy", "apellido": "MacFadden", "email": "rmacfaddenc@phoca.cz", "genero": "Male", "edad": 37}, {"nombre": 14, "id": "Liam", "apellido": "Glazier", "email": "lglazierd@bloomberg.com", "genero": "Male", "edad": 56}, {"nombre": 15, "id": "Lenci", "apellido": "MacCaull", "email": "lmaccaulle@phoca.cz", "genero": "Male", "edad": 60}, {"nombre": 16, "id": "Giacopo", "apellido": "Fuggles", "email": "gfugglesf@icio.us", "genero": "Male", "edad": 43}, {"nombre": 17, "id": "Gearard", "apellido": "Emeline", "email": "gemelineg@mail.ru", "genero": "Bigender", "edad": 24}, {"nombre": 18, "id": "Conan", "apellido": "Chrichton", "email": "cchrichtonh@nytimes.com", "genero": "Male", "edad": 41}, {"nombre": 19, "id": "Francesca", "apellido": "Whatling", "email": "fwhatlingi@youku.com", "genero": "Female", "edad": 56}, {"nombre": 20, "id": "Paul", "apellido": "Have", "email": "phavej@example.com", "genero": "Male", "edad": 39}, {"nombre": 21, "id": "Nat", "apellido": "Pitkeathly", "email": "npitkeathlyk@instagram.com", "genero": "Female", "edad": 55}, {"nombre": 22, "id": "Lorry", "apellido": "Morratt", "email": "lmorrattl@discovery.com", "genero": "Female", "edad": 60}, {"nombre": 23, "id": "Fiann", "apellido": "Jeacock", "email": "fjeacockm@yandex.ru", "genero": "Female", "edad": 43}, {"nombre": 24, "id": "Marge", "apellido": "Sole", "email": "msolen@ox.ac.uk", "genero": "Female", "edad": 65}, {"nombre": 25, "id": "Eveline", "apellido": "Cordrey", "email": "ecordreyo@list-manage.com", "genero": "Female", "edad": 55}, {"nombre": 26, "id": "Minetta", "apellido": "Guile", "email": "mguilep@mapquest.com", "genero": "Female", "edad": 51}, {"nombre": 27, "id": "Heath", "apellido": "Corkett", "email": "hcorkettq@yahoo.com", "genero": "Male", "edad": 31}, {"nombre": 28, "id": "Olvan", "apellido": "Jeaffreson", "email": "ojeaffresonr@chicagotribune.com", "genero": "Male", "edad": 32}, {"nombre": 29, "id": "Lacie", "apellido": "Pizey", "email": "lpizeys@boston.com", "genero": "Female", "edad": 34}, {"nombre": 30, "id": "Bonny", "apellido": "Brumhead", "email": "bbrumheadt@stumbleupon.com", "genero": "Female", "edad": 43}, {"nombre": 31, "id": "Rivi", "apellido": "Finch", "email": "rfinchu@jiathis.com", "genero": "Female", "edad": 52}, {"nombre": 32, "id": "Sigismondo", "apellido": "Becks", "email": "sbecksv@taobao.com", "genero": "Male", "edad": 42}, {"nombre": 33, "id": "Ezechiel", "apellido": "Stackbridge", "email": "estackbridgew@sciencedaily.com", "genero": "Male", "edad": 26}, {"nombre": 34, "id": "Kathye", "apellido": "Stilwell", "email": "kstilwellx@zimbio.com", "genero": "Female", "edad": 47}, {"nombre": 35, "id": "Fran", "apellido": "Iacovuzzi", "email": "fiacovuzziy@comsenz.com", "genero": "Female", "edad": 55}, {"nombre": 36, "id": "Teodor", "apellido": "Bowerman", "email": "tbowermanz@jalbum.net", "genero": "Male", "edad": 64}, {"nombre": 37, "id": "Aretha", "apellido": "Josiah", "email": "ajosiah10@godaddy.com", "genero": "Female", "edad": 24}, {"nombre": 38, "id": "Suzann", "apellido": "Dove", "email": "sdove11@feedburner.com", "genero": "Female", "edad": 29}, {"nombre": 39, "id": "Sherm", "apellido": "Robke", "email": "srobke12@vistaprint.com", "genero": "Male", "edad": 61}, {"nombre": 40, "id": "Jsandye", "apellido": "Dannell", "email": "jdannell13@godaddy.com", "genero": "Female", "edad": 43}, {"nombre": 41, "id": "Fairlie", "apellido": "Castan", "email": "fcastan14@cdbaby.com", "genero": "Male", "edad": 30}, {"nombre": 42, "id": "Jamima", "apellido": "Beardshaw", "email": "jbeardshaw15@google.es", "genero": "Female", "edad": 26}, {"nombre": 43, "id": "Gwenni", "apellido": "Spyvye", "email": "gspyvye16@github.com", "genero": "Female", "edad": 19}, {"nombre": 44, "id": "Keefe", "apellido": "Roselli", "email": "kroselli17@auda.org.au", "genero": "Male", "edad": 58}, {"nombre": 45, "id": "Nataniel", "apellido": "Bettenay", "email": "nbettenay18@yellowbook.com", "genero": "Male", "edad": 27}, {"nombre": 46, "id": "Gerry", "apellido": "Avramovich", "email": "gavramovich19@apple.com", "genero": "Female", "edad": 26}, {"nombre": 47, "id": "Felecia", "apellido": "Strank", "email": "fstrank1a@miitbeian.gov.cn", "genero": "Female", "edad": 33}, {"nombre": 48, "id": "Floyd", "apellido": "Aburrow", "email": "faburrow1b@wordpress.org", "genero": "Male", "edad": 46}, {"nombre": 49, "id": "Lazar", "apellido": "Kerner", "email": "lkerner1c@mashable.com", "genero": "Male", "edad": 29}, {"nombre": 50, "id": "Antonetta", "apellido": "Doring", "email": "adoring1d@gmpg.org", "genero": "Female", "edad": 28}]}